<?xml version="1.0" encoding="UTF-8"?>
<configuration> <inputFileUrl>https://raw.githubusercontent.com/wlpotter/draft-data/master/data/bethqatraye-TSVTransform/placesToTransformBethQatraye.csv</inputFileUrl>
  <localPath>temp/syriaca/</localPath>
  <outputTo>console</outputTo>
  <mintedString>William L. Potter</mintedString>
  <mintedUri>http://syriaca.org/documentation/editors.xml#wpotter</mintedUri>
  <sponsorList>
    <sponsor>Syriaca.org: The Syriac Reference Portal</sponsor>
  </sponsorList>
  <funderList>
    <funder>The National Endowment for the Humanities</funder>
    <funder>The International Balzan Prize Foundation</funder>
  </funderList>
  <principal>David A. Michelson</principal><!--Can there be multiple principal elements? There can be multiple principal researchers...-->
  <editorList>
    <editor>
      <editorString>Thomas A. Carlson</editorString>
      <editorUri>http://syriaca.org/documentation/editors.xml#tcarlson</editorUri>
      <editorRole>general</editorRole>
    </editor>
    <editor>
      <editorString>Thomas A. Carlson</editorString>
      <editorUri>http://syriaca.org/documentation/editors.xml#tcarlson</editorUri>
      <editorRole>creator</editorRole>
    </editor>
    <editor>
      <editorString>David A. Michelson</editorString>
      <editorUri>http://syriaca.org/documentation/editors.xml#dmichelson</editorUri>
      <editorRole>general</editorRole>
    </editor>
  </editorList>
  <respStmtList>
    <respStmt>
      <respString>Data merging, Wikipedia linking, and XML by</respString>
      <nameString>Thomas A. Carlson</nameString>
      <nameUri>http://syriaca.org/documentation/editors.xml#tcarlson</nameUri>
    </respStmt>
    <respStmt>
      <respString>Ibn al-Faqih data collection by</respString>
      <nameString>Saif al-Murikhi</nameString>
      <nameUri>http://syriaca.org/documentation/editors.xml#sal-murikhi</nameUri>
    </respStmt>
  </respStmtList>
</configuration>