<?xml version="1.0" encoding="UTF-8"?>
<rdf:RDF xmlns:lawd="http://lawd.info/ontology/" xmlns:owl="http://www.w3.org/2002/07/owl#"
    xmlns:rdf="http://www.w3.org/1999/02/22-rdf-syntax-ns#"
    xmlns:rdfs="http://www.w3.org/2000/01/rdf-schema#"
    xmlns:modsrdf="http://www.loc.gov/standards/mods/modsrdf/v1/modsrdf.owl"
    xmlns:dcterms="http://purl.org/dc/terms/">
    <rdf:Description rdf:about="http://cwkb.org/work/id/1411/rdf">
        <rdf:type rdf:resource="http://lawd.info/ontology/conceptualWork"/>
        <lawd:responsibleAgent>http://cwkb.org/author/id/678/rdf</lawd:responsibleAgent>
        <rdfs:label xml:lang="la">Eclogae</rdfs:label>
        <rdfs:label xml:lang="es">Bucólicas</rdfs:label>
        <rdfs:label xml:lang="es">Églogas</rdfs:label>
        <rdfs:label xml:lang="la">Bucolica</rdfs:label>
        <rdfs:label xml:lang="it">Bucoliche</rdfs:label>
        <rdfs:label xml:lang="it">Egloghe</rdfs:label>
        <rdfs:label xml:lang="de">Eklogen</rdfs:label>
        <rdfs:label xml:lang="de">Hirtengedichte</rdfs:label>
        <rdfs:label xml:lang="fr">Bucoliques</rdfs:label>
        <rdfs:label xml:lang="fr">Éclogues</rdfs:label>
        <rdfs:label xml:lang="en">Bucolics</rdfs:label>
        <rdfs:label xml:lang="en">Eclogues</rdfs:label>
        <lawd:abbreviation>ecl.</lawd:abbreviation>
        <dcterms:identifier>phi:0690.001</dcterms:identifier>
        <dcterms:identifier>urn:cts:latinLit:phi0690.phi001</dcterms:identifier>
        <dcterms:language>latin</dcterms:language>
        <owl:sameAs rdf:resource="http://data.perseus.org/catalog/urn:cts:latinLit:phi0690.phi001"/>
        <lawd:Citation>http://cwkb.org/resolver?rft.auauthority=P. Vergilius
            Maro&amp;rft.titleauthority=Eclogae&amp;rft_val_fmt=info:ofi/fmt:kev:mtx:canonical_cit&amp;ctx_ver=Z39.88-2004</lawd:Citation>
    </rdf:Description>
</rdf:RDF>
